{
    "name": {
        "_info": {
            "comment": "",
            "filledWith": "testeth 1.6.0-alpha.0-11+commit.978e68d2",
            "lllcversion": "Version: 0.5.0-develop.2018.11.9+commit.9709dfe0.Linux.g++",
            "source": "src/GeneralStateTestsFiller/stRevertTest/RevertPrefoundOOGFiller.json",
            "sourceHash": "4143662442473b382c03d026df789489efaf43e5f790671d94234d0b874fe19a"
        },
        "env": {
            "currentCoinbase": "2adc25665018aa1fe0e6bc666dac8fc2697ff9ba",
            "currentDifficulty": "0x20000",
            "currentGasLimit": "0x989680",
            "currentNumber": "0x1",
            "currentTimestamp": "0x3e8"
        },
        "pre": {
            "0x7db299e0885c85039f56fa504a13dd8ce8a56aa7": {
                "balance": "0x1"
            },
            "0xa000000000000000000000000000000000000000": {
                "code": "0x602060006000f0600055600c600155",
                "balance": "0x1"
            },
            "0xa94f5374fce5edbc8e2a8697c15331677e6ebf0b": {
                "balance": "0xe8d4a51000"
            }
        },
        "transaction": {
            "gasPrice": "0x1",
            "nonce": "0x0",
            "to": "0xa000000000000000000000000000000000000000",
            "data": [
                "0x"
            ],
            "gasLimit": [
                "0x16b48"
            ],
            "value": [
                "0x00"
            ],
            "secretKey": "0x45a915e4d060149eb4365960e6a7a45f334393093061116b197e3240065ff2d8"
        },
        "post": {
            "Byzantium": [
                {
                    "hash": "d059b45833134777f23eca1eb256ca5a2451fc5ecea41e0cc8f581faccdf385e",
                    "logs": "1dcc4de8dec75d7aab85b567b6ccd41ad312451b948a7413f0a142fd40d49347",
                    "indexes": {
                        "data": 0,
                        "gas": 0,
                        "value": 0
                    }
                }
            ],
            "ClassicAtlantis": [
                {
                    "hash": "d059b45833134777f23eca1eb256ca5a2451fc5ecea41e0cc8f581faccdf385e",
                    "logs": "1dcc4de8dec75d7aab85b567b6ccd41ad312451b948a7413f0a142fd40d49347",
                    "indexes": {
                        "data": 0,
                        "gas": 0,
                        "value": 0
                    }
                }
            ],
            "Constantinople": [
                {
                    "hash": "d059b45833134777f23eca1eb256ca5a2451fc5ecea41e0cc8f581faccdf385e",
                    "logs": "1dcc4de8dec75d7aab85b567b6ccd41ad312451b948a7413f0a142fd40d49347",
                    "indexes": {
                        "data": 0,
                        "gas": 0,
                        "value": 0
                    }
                }
            ],
            "ConstantinopleFix": [
                {
                    "hash": "d059b45833134777f23eca1eb256ca5a2451fc5ecea41e0cc8f581faccdf385e",
                    "logs": "1dcc4de8dec75d7aab85b567b6ccd41ad312451b948a7413f0a142fd40d49347",
                    "indexes": {
                        "data": 0,
                        "gas": 0,
                        "value": 0
                    }
                }
            ],
            "EIP150": [
                {
                    "hash": "d059b45833134777f23eca1eb256ca5a2451fc5ecea41e0cc8f581faccdf385e",
                    "logs": "1dcc4de8dec75d7aab85b567b6ccd41ad312451b948a7413f0a142fd40d49347",
                    "indexes": {
                        "data": 0,
                        "gas": 0,
                        "value": 0
                    }
                }
            ],
            "EIP158": [
                {
                    "hash": "d059b45833134777f23eca1eb256ca5a2451fc5ecea41e0cc8f581faccdf385e",
                    "logs": "1dcc4de8dec75d7aab85b567b6ccd41ad312451b948a7413f0a142fd40d49347",
                    "indexes": {
                        "data": 0,
                        "gas": 0,
                        "value": 0
                    }
                }
            ],
            "Homestead": [
                {
                    "hash": "d059b45833134777f23eca1eb256ca5a2451fc5ecea41e0cc8f581faccdf385e",
                    "logs": "1dcc4de8dec75d7aab85b567b6ccd41ad312451b948a7413f0a142fd40d49347",
                    "indexes": {
                        "data": 0,
                        "gas": 0,
                        "value": 0
                    }
                }
            ]
        }
    }
}